pytest_fauxfactory/__init__.py
pytest_fauxfactory/constants.py
pytest_fauxfactory/handlers.py
pytest_fauxfactory/helpers.py
pytest_fauxfactory/marks.py
pytest_fauxfactory/plugin.py
pytest_fauxfactory-1.1.1.dist-info/DESCRIPTION.rst
pytest_fauxfactory-1.1.1.dist-info/METADATA
pytest_fauxfactory-1.1.1.dist-info/RECORD
pytest_fauxfactory-1.1.1.dist-info/WHEEL
pytest_fauxfactory-1.1.1.dist-info/entry_points.txt
pytest_fauxfactory-1.1.1.dist-info/metadata.json
pytest_fauxfactory-1.1.1.dist-info/top_level.txt
