Metadata-Version: 2.0
Name: pytest-fauxfactory
Version: 1.1.1
Summary: Integration of fauxfactory into pytest.
Home-page: https://github.com/omaciel/pytest-fauxfactory
Author: Og Maciel
Author-email: omaciel@ogmaciel.com
License: GPLv3
Keywords: pytest
Platform: UNKNOWN
Classifier: Topic :: Utilities
Classifier: Development Status :: 5 - Production/Stable
Classifier: Intended Audience :: Developers
Classifier: Natural Language :: English
Classifier: License :: OSI Approved :: GNU General Public License v3 (GPLv3)
Classifier: Programming Language :: Python
Classifier: Programming Language :: Python :: 2.7
Classifier: Programming Language :: Python :: 3.4
Classifier: Programming Language :: Python :: 3.5
Classifier: Programming Language :: Python :: 3.6
Classifier: Topic :: Software Development :: Testing
Requires-Dist: pytest (>=3.2)
Requires-Dist: fauxfactory
Provides-Extra: dev
Requires-Dist: coverage; extra == 'dev'
Requires-Dist: flake8; extra == 'dev'
Requires-Dist: pytest-xdist; extra == 'dev'
Requires-Dist: twine; extra == 'dev'
Requires-Dist: wheel; extra == 'dev'
